Yadab_STT/__init__.py
yadab_stt-0.1.dist-info/METADATA
yadab_stt-0.1.dist-info/WHEEL
yadab_stt-0.1.dist-info/top_level.txt
yadab_stt-0.1.dist-info/RECORD
