Metadata-Version: 2.4
Name: yadab_STT
Version: 0.1
Summary: this is speech to text package created by yadab rokka
Author: YadabRokka
Author-email: rokkabibash1@gmail.com
Dynamic: author
Dynamic: author-email
Dynamic: summary
